{"assets":{"594DD3763D6DF4DD8985F7652A5E1E22":{"type":"texture","index":60,"assetRequest":{"type":"slide","state":"text","slide":"5C56AAAE-40E4-44FE-9BAD-A706131CB1B3"},"url":{"web":"assets/594DD3763D6DF4DD8985F7652A5E1E22.svg"},"width":777,"height":44},"017C668F998B7F15E9E4969BA01E1547":{"type":"texture","index":66,"assetRequest":{"type":"slide","state":"text","slide":"5C56AAAE-40E4-44FE-9BAD-A706131CB1B3"},"url":{"web":"assets/017C668F998B7F15E9E4969BA01E1547.svg"},"width":605,"height":55},"1271778CB81AA6A50AC86F5223E5A8DE":{"type":"texture","index":65,"assetRequest":{"type":"slide","state":"text","slide":"5C56AAAE-40E4-44FE-9BAD-A706131CB1B3"},"url":{"web":"assets/1271778CB81AA6A50AC86F5223E5A8DE.svg"},"width":851,"height":49},"498E23C82CA78A4BCD7BA88E5243B6FC":{"type":"texture","index":57,"assetRequest":{"type":"slide","state":"background","slide":"5C56AAAE-40E4-44FE-9BAD-A706131CB1B3"},"url":{"web":"assets/498E23C82CA78A4BCD7BA88E5243B6FC.svg"},"width":1024,"height":768},"109D68C7090F2FDAA0DF4E7A1E94D247":{"type":"texture","index":71,"assetRequest":{"type":"slide","state":"text","slide":"5C56AAAE-40E4-44FE-9BAD-A706131CB1B3"},"url":{"web":"assets/109D68C7090F2FDAA0DF4E7A1E94D247.svg"},"width":511,"height":45},"DC8E691884F75FE1807FEC32BDA4A5F3":{"type":"texture","index":67,"assetRequest":{"type":"slide","state":"text","slide":"5C56AAAE-40E4-44FE-9BAD-A706131CB1B3"},"url":{"web":"assets/DC8E691884F75FE1807FEC32BDA4A5F3.svg"},"width":915,"height":47},"45AED0194D76030045A33608F1C5935F":{"type":"texture","index":59,"assetRequest":{"type":"slide","state":"text","slide":"5C56AAAE-40E4-44FE-9BAD-A706131CB1B3"},"url":{"web":"assets/45AED0194D76030045A33608F1C5935F.svg"},"width":806,"height":44},"B47C72EEE3C5FCFD1CE0804F1B8DC033":{"type":"texture","index":61,"assetRequest":{"type":"slide","state":"text","slide":"5C56AAAE-40E4-44FE-9BAD-A706131CB1B3"},"url":{"web":"assets/B47C72EEE3C5FCFD1CE0804F1B8DC033.svg"},"width":400,"height":43},"3566B8F5A3052C3CFC02C486841F1578":{"type":"texture","index":70,"assetRequest":{"type":"slide","state":"text","slide":"5C56AAAE-40E4-44FE-9BAD-A706131CB1B3"},"url":{"web":"assets/3566B8F5A3052C3CFC02C486841F1578.svg"},"width":513,"height":36},"57815644117D774ADB2AE5FF763EFF69":{"type":"texture","index":68,"assetRequest":{"type":"slide","state":"text","slide":"5C56AAAE-40E4-44FE-9BAD-A706131CB1B3"},"url":{"web":"assets/57815644117D774ADB2AE5FF763EFF69.svg"},"width":686,"height":45},"5C6FE352E1A9717F70C38CF9737A0768":{"type":"texture","index":58,"assetRequest":{"type":"slide","state":"text","slide":"5C56AAAE-40E4-44FE-9BAD-A706131CB1B3"},"url":{"web":"assets/5C6FE352E1A9717F70C38CF9737A0768.svg"},"width":846,"height":50},"D984BE9F520E639DDDAE398166E6BAAD":{"type":"texture","index":62,"assetRequest":{"type":"slide","state":"text","slide":"5C56AAAE-40E4-44FE-9BAD-A706131CB1B3"},"url":{"web":"assets/D984BE9F520E639DDDAE398166E6BAAD.svg"},"width":819,"height":49},"A3E4EFD9794FB7642995D2C77814E950":{"type":"texture","index":63,"assetRequest":{"type":"slide","state":"text","slide":"5C56AAAE-40E4-44FE-9BAD-A706131CB1B3"},"url":{"web":"assets/A3E4EFD9794FB7642995D2C77814E950.svg"},"width":741,"height":44},"D9D14FC9304218BE071BFC518A61B9F3":{"type":"texture","index":64,"assetRequest":{"type":"slide","state":"text","slide":"5C56AAAE-40E4-44FE-9BAD-A706131CB1B3"},"url":{"web":"assets/D9D14FC9304218BE071BFC518A61B9F3.svg"},"width":481,"height":49},"40771467E7D8A9D109D564F1F5A5F8AD":{"type":"texture","index":72,"assetRequest":{"type":"slide","state":"text","slide":"5C56AAAE-40E4-44FE-9BAD-A706131CB1B3"},"url":{"web":"assets/40771467E7D8A9D109D564F1F5A5F8AD.svg"},"width":954,"height":51},"3516134BABE37B77441AD23AA08AB556":{"type":"texture","index":69,"assetRequest":{"type":"slide","state":"text","slide":"5C56AAAE-40E4-44FE-9BAD-A706131CB1B3"},"url":{"web":"assets/3516134BABE37B77441AD23AA08AB556.svg"},"width":793,"height":51}},"events":[{"effects":[{"beginTime":0,"baseLayer":{"animations":[],"initialState":{"affineTransform":[1,0,0,1,0,0],"masksToBounds":false,"rotation":0,"scale":1,"position":{"pointX":512,"pointY":384},"width":1024,"sublayerTransform":[1,0,0,0,0,1,0,0,0,0,1,0,0,0,0,1],"contentsRect":{"y":0,"x":0,"width":1,"height":1},"opacity":1,"edgeAntialiasingMask":251658240,"height":768,"hidden":false,"anchorPoint":{"pointX":0.5,"pointY":0.5}},"objectID":"0","layers":[{"animations":[],"initialState":{"affineTransform":[1,0,0,1,0,0],"masksToBounds":false,"rotation":0,"scale":1,"position":{"pointX":512,"pointY":384},"width":1024,"sublayerTransform":[1,0,0,0,0,1,0,0,0,0,1,-0.0004922987690640373,0,0,0,1],"contentsRect":{"y":0,"x":0,"width":1,"height":1},"opacity":1,"edgeAntialiasingMask":251658240,"height":768,"hidden":false,"anchorPoint":{"pointX":0.5,"pointY":0.5}},"layers":[{"animations":[{"timeOffset":0,"beginTime":0,"repeatCount":0,"animations":[{"timeOffset":0,"from":{"scalar":0},"beginTime":0,"repeatCount":0,"fillMode":"both","duration":2,"autoreverses":false,"timingFunction":"EaseInEaseOut","property":"zPosition","to":{"scalar":0}}],"fillMode":"both","autoreverses":false,"duration":2}],"initialState":{"affineTransform":[1,0,0,1,0,0],"masksToBounds":false,"rotation":0,"scale":1,"position":{"pointX":512,"pointY":384},"width":1024,"sublayerTransform":[1,0,0,0,0,1,0,0,0,0,1,0,0,0,0,1],"contentsRect":{"y":0,"x":0,"width":1,"height":1},"opacity":1,"edgeAntialiasingMask":251658240,"height":768,"hidden":false,"anchorPoint":{"pointX":0.5,"pointY":0.5}},"layers":[{"animations":[],"layers":[],"initialState":{"affineTransform":[1,0,0,1,0,0],"masksToBounds":false,"rotation":0,"scale":1,"position":{"pointX":512,"pointY":384},"width":1024,"sublayerTransform":[1,0,0,0,0,1,0,0,0,0,1,0,0,0,0,1],"contentsRect":{"y":0,"x":0,"width":1,"height":1},"opacity":1,"edgeAntialiasingMask":0,"height":768,"hidden":false,"anchorPoint":{"pointX":0.5,"pointY":0.5}},"texture":"498E23C82CA78A4BCD7BA88E5243B6FC"}]}]},{"animations":[{"timeOffset":0,"beginTime":0,"repeatCount":0,"animations":[{"timeOffset":0,"from":{"scalar":0.001},"beginTime":0,"repeatCount":0,"fillMode":"both","duration":2,"autoreverses":false,"timingFunction":"EaseInEaseOut","property":"zPosition","to":{"scalar":0.001}}],"fillMode":"both","autoreverses":false,"duration":2}],"initialState":{"affineTransform":[1,0,0,1,0,0],"masksToBounds":false,"rotation":0,"scale":1,"position":{"pointX":511.5,"pointY":383.5},"width":903,"sublayerTransform":[1,0,0,0,0,1,0,0,0,0,1,0,0,0,0,1],"contentsRect":{"y":0,"x":0,"width":1,"height":1},"opacity":1,"edgeAntialiasingMask":251658240,"height":647,"hidden":false,"anchorPoint":{"pointX":0.5,"pointY":0.5}},"layers":[{"animations":[{"timeOffset":0,"beginTime":0,"repeatCount":0,"animations":[{"timeOffset":0,"from":{"scalar":1},"beginTime":0,"repeatCount":0,"fillMode":"forwards","duration":2,"autoreverses":false,"timingFunction":"EaseInEaseOut","property":"opacity","to":{"scalar":0}},{"timeOffset":0,"from":{"scalar":true},"beginTime":1.998,"repeatCount":0,"fillMode":"forwards","property":"hidden","autoreverses":false,"duration":0.002000000000000002,"to":{"scalar":true}}],"fillMode":"both","autoreverses":false,"duration":2}],"layers":[],"initialState":{"affineTransform":[1,0,0,1,0,0],"masksToBounds":false,"rotation":0,"scale":1,"position":{"pointX":451.5000000000001,"pointY":323.5},"width":846,"sublayerTransform":[1,0,0,0,0,1,0,0,0,0,1,0,0,0,0,1],"contentsRect":{"y":0,"x":0,"width":1,"height":1},"opacity":1,"edgeAntialiasingMask":0,"height":50,"hidden":false,"anchorPoint":{"pointX":0.5289598108747046,"pointY":6.31}},"texture":"5C6FE352E1A9717F70C38CF9737A0768"}]},{"animations":[{"timeOffset":0,"beginTime":0,"repeatCount":0,"animations":[{"timeOffset":0,"from":{"scalar":0.002},"beginTime":0,"repeatCount":0,"fillMode":"both","duration":2,"autoreverses":false,"timingFunction":"EaseInEaseOut","property":"zPosition","to":{"scalar":0.002}}],"fillMode":"both","autoreverses":false,"duration":2}],"initialState":{"affineTransform":[1,0,0,1,0,0],"masksToBounds":false,"rotation":0,"scale":1,"position":{"pointX":511.5,"pointY":383.5},"width":903,"sublayerTransform":[1,0,0,0,0,1,0,0,0,0,1,0,0,0,0,1],"contentsRect":{"y":0,"x":0,"width":1,"height":1},"opacity":1,"edgeAntialiasingMask":251658240,"height":647,"hidden":false,"anchorPoint":{"pointX":0.5,"pointY":0.5}},"layers":[{"animations":[{"timeOffset":0,"beginTime":0,"repeatCount":0,"animations":[{"timeOffset":0,"from":{"scalar":1},"beginTime":0,"repeatCount":0,"fillMode":"forwards","duration":2,"autoreverses":false,"timingFunction":"EaseInEaseOut","property":"opacity","to":{"scalar":0}},{"timeOffset":0,"from":{"scalar":true},"beginTime":1.998,"repeatCount":0,"fillMode":"forwards","property":"hidden","autoreverses":false,"duration":0.002000000000000002,"to":{"scalar":true}}],"fillMode":"both","autoreverses":false,"duration":2}],"layers":[],"initialState":{"affineTransform":[1,0,0,1,0,0],"masksToBounds":false,"rotation":0,"scale":1,"position":{"pointX":451.5,"pointY":323.5},"width":806,"sublayerTransform":[1,0,0,0,0,1,0,0,0,0,1,0,0,0,0,1],"contentsRect":{"y":0,"x":0,"width":1,"height":1},"opacity":1,"edgeAntialiasingMask":0,"height":44,"hidden":false,"anchorPoint":{"pointX":0.510545905707196,"pointY":5.534090909090909}},"texture":"45AED0194D76030045A33608F1C5935F"}]},{"animations":[{"timeOffset":0,"beginTime":0,"repeatCount":0,"animations":[{"timeOffset":0,"from":{"scalar":0.003},"beginTime":0,"repeatCount":0,"fillMode":"both","duration":2,"autoreverses":false,"timingFunction":"EaseInEaseOut","property":"zPosition","to":{"scalar":0.003}}],"fillMode":"both","autoreverses":false,"duration":2}],"initialState":{"affineTransform":[1,0,0,1,0,0],"masksToBounds":false,"rotation":0,"scale":1,"position":{"pointX":511.5,"pointY":383.5},"width":903,"sublayerTransform":[1,0,0,0,0,1,0,0,0,0,1,0,0,0,0,1],"contentsRect":{"y":0,"x":0,"width":1,"height":1},"opacity":1,"edgeAntialiasingMask":251658240,"height":647,"hidden":false,"anchorPoint":{"pointX":0.5,"pointY":0.5}},"layers":[{"animations":[{"timeOffset":0,"beginTime":0,"repeatCount":0,"animations":[{"timeOffset":0,"from":{"scalar":1},"beginTime":0,"repeatCount":0,"fillMode":"forwards","duration":2,"autoreverses":false,"timingFunction":"EaseInEaseOut","property":"opacity","to":{"scalar":0}},{"timeOffset":0,"from":{"scalar":true},"beginTime":1.998,"repeatCount":0,"fillMode":"forwards","property":"hidden","autoreverses":false,"duration":0.002000000000000002,"to":{"scalar":true}}],"fillMode":"both","autoreverses":false,"duration":2}],"layers":[],"initialState":{"affineTransform":[1,0,0,1,0,0],"masksToBounds":false,"rotation":0,"scale":1,"position":{"pointX":451.5,"pointY":323.5},"width":777,"sublayerTransform":[1,0,0,0,0,1,0,0,0,0,1,0,0,0,0,1],"contentsRect":{"y":0,"x":0,"width":1,"height":1},"opacity":1,"edgeAntialiasingMask":0,"height":44,"hidden":false,"anchorPoint":{"pointX":0.5296010296010296,"pointY":4.034090909090909}},"texture":"594DD3763D6DF4DD8985F7652A5E1E22"}]},{"animations":[{"timeOffset":0,"beginTime":0,"repeatCount":0,"animations":[{"timeOffset":0,"from":{"scalar":0.004},"beginTime":0,"repeatCount":0,"fillMode":"both","duration":2,"autoreverses":false,"timingFunction":"EaseInEaseOut","property":"zPosition","to":{"scalar":0.004}}],"fillMode":"both","autoreverses":false,"duration":2}],"initialState":{"affineTransform":[1,0,0,1,0,0],"masksToBounds":false,"rotation":0,"scale":1,"position":{"pointX":511.5,"pointY":383.5},"width":903,"sublayerTransform":[1,0,0,0,0,1,0,0,0,0,1,0,0,0,0,1],"contentsRect":{"y":0,"x":0,"width":1,"height":1},"opacity":1,"edgeAntialiasingMask":251658240,"height":647,"hidden":false,"anchorPoint":{"pointX":0.5,"pointY":0.5}},"layers":[{"animations":[{"timeOffset":0,"beginTime":0,"repeatCount":0,"animations":[{"timeOffset":0,"from":{"scalar":1},"beginTime":0,"repeatCount":0,"fillMode":"forwards","duration":2,"autoreverses":false,"timingFunction":"EaseInEaseOut","property":"opacity","to":{"scalar":0}},{"timeOffset":0,"from":{"scalar":true},"beginTime":1.998,"repeatCount":0,"fillMode":"forwards","property":"hidden","autoreverses":false,"duration":0.002000000000000002,"to":{"scalar":true}}],"fillMode":"both","autoreverses":false,"duration":2}],"layers":[],"initialState":{"affineTransform":[1,0,0,1,0,0],"masksToBounds":false,"rotation":0,"scale":1,"position":{"pointX":451.5,"pointY":323.5},"width":400,"sublayerTransform":[1,0,0,0,0,1,0,0,0,0,1,0,0,0,0,1],"contentsRect":{"y":0,"x":0,"width":1,"height":1},"opacity":1,"edgeAntialiasingMask":0,"height":43,"hidden":false,"anchorPoint":{"pointX":1.02875,"pointY":0.1046511627906977}},"texture":"B47C72EEE3C5FCFD1CE0804F1B8DC033"}]},{"animations":[{"timeOffset":0,"beginTime":0,"repeatCount":0,"animations":[{"timeOffset":0,"from":{"scalar":0.005},"beginTime":0,"repeatCount":0,"fillMode":"both","duration":2,"autoreverses":false,"timingFunction":"EaseInEaseOut","property":"zPosition","to":{"scalar":0.005}}],"fillMode":"both","autoreverses":false,"duration":2}],"initialState":{"affineTransform":[1,0,0,1,0,0],"masksToBounds":false,"rotation":0,"scale":1,"position":{"pointX":511.5,"pointY":383.5},"width":903,"sublayerTransform":[1,0,0,0,0,1,0,0,0,0,1,0,0,0,0,1],"contentsRect":{"y":0,"x":0,"width":1,"height":1},"opacity":1,"edgeAntialiasingMask":251658240,"height":647,"hidden":false,"anchorPoint":{"pointX":0.5,"pointY":0.5}},"layers":[{"animations":[{"timeOffset":0,"beginTime":0,"repeatCount":0,"animations":[{"timeOffset":0,"from":{"scalar":1},"beginTime":0,"repeatCount":0,"fillMode":"forwards","duration":2,"autoreverses":false,"timingFunction":"EaseInEaseOut","property":"opacity","to":{"scalar":0}},{"timeOffset":0,"from":{"scalar":true},"beginTime":1.998,"repeatCount":0,"fillMode":"forwards","property":"hidden","autoreverses":false,"duration":0.002000000000000002,"to":{"scalar":true}}],"fillMode":"both","autoreverses":false,"duration":2}],"layers":[],"initialState":{"affineTransform":[1,0,0,1,0,0],"masksToBounds":false,"rotation":0,"scale":1,"position":{"pointX":451.5000000000001,"pointY":323.5},"width":819,"sublayerTransform":[1,0,0,0,0,1,0,0,0,0,1,0,0,0,0,1],"contentsRect":{"y":0,"x":0,"width":1,"height":1},"opacity":1,"edgeAntialiasingMask":0,"height":49,"hidden":false,"anchorPoint":{"pointX":0.5463980463980465,"pointY":1.561224489795918}},"texture":"D984BE9F520E639DDDAE398166E6BAAD"}]},{"animations":[{"timeOffset":0,"beginTime":0,"repeatCount":0,"animations":[{"timeOffset":0,"from":{"scalar":0.006},"beginTime":0,"repeatCount":0,"fillMode":"both","duration":2,"autoreverses":false,"timingFunction":"EaseInEaseOut","property":"zPosition","to":{"scalar":0.006}}],"fillMode":"both","autoreverses":false,"duration":2}],"initialState":{"affineTransform":[1,0,0,1,0,0],"masksToBounds":false,"rotation":0,"scale":1,"position":{"pointX":511.5,"pointY":383.5},"width":903,"sublayerTransform":[1,0,0,0,0,1,0,0,0,0,1,0,0,0,0,1],"contentsRect":{"y":0,"x":0,"width":1,"height":1},"opacity":1,"edgeAntialiasingMask":251658240,"height":647,"hidden":false,"anchorPoint":{"pointX":0.5,"pointY":0.5}},"layers":[{"animations":[{"timeOffset":0,"beginTime":0,"repeatCount":0,"animations":[{"timeOffset":0,"from":{"scalar":1},"beginTime":0,"repeatCount":0,"fillMode":"forwards","duration":2,"autoreverses":false,"timingFunction":"EaseInEaseOut","property":"opacity","to":{"scalar":0}},{"timeOffset":0,"from":{"scalar":true},"beginTime":1.998,"repeatCount":0,"fillMode":"forwards","property":"hidden","autoreverses":false,"duration":0.002000000000000002,"to":{"scalar":true}}],"fillMode":"both","autoreverses":false,"duration":2}],"layers":[],"initialState":{"affineTransform":[1,0,0,1,0,0],"masksToBounds":false,"rotation":0,"scale":1,"position":{"pointX":451.5,"pointY":323.5},"width":741,"sublayerTransform":[1,0,0,0,0,1,0,0,0,0,1,0,0,0,0,1],"contentsRect":{"y":0,"x":0,"width":1,"height":1},"opacity":1,"edgeAntialiasingMask":0,"height":44,"hidden":false,"anchorPoint":{"pointX":0.5553306342780027,"pointY":-3.806818181818182}},"texture":"A3E4EFD9794FB7642995D2C77814E950"}]},{"animations":[{"timeOffset":0,"beginTime":0,"repeatCount":0,"animations":[{"timeOffset":0,"from":{"scalar":0.007},"beginTime":0,"repeatCount":0,"fillMode":"both","duration":2,"autoreverses":false,"timingFunction":"EaseInEaseOut","property":"zPosition","to":{"scalar":0.007}}],"fillMode":"both","autoreverses":false,"duration":2}],"initialState":{"affineTransform":[1,0,0,1,0,0],"masksToBounds":false,"rotation":0,"scale":1,"position":{"pointX":511.5,"pointY":383.5},"width":903,"sublayerTransform":[1,0,0,0,0,1,0,0,0,0,1,0,0,0,0,1],"contentsRect":{"y":0,"x":0,"width":1,"height":1},"opacity":1,"edgeAntialiasingMask":251658240,"height":647,"hidden":false,"anchorPoint":{"pointX":0.5,"pointY":0.5}},"layers":[{"animations":[{"timeOffset":0,"beginTime":0,"repeatCount":0,"animations":[{"timeOffset":0,"from":{"scalar":1},"beginTime":0,"repeatCount":0,"fillMode":"forwards","duration":2,"autoreverses":false,"timingFunction":"EaseInEaseOut","property":"opacity","to":{"scalar":0}},{"timeOffset":0,"from":{"scalar":true},"beginTime":1.998,"repeatCount":0,"fillMode":"forwards","property":"hidden","autoreverses":false,"duration":0.002000000000000002,"to":{"scalar":true}}],"fillMode":"both","autoreverses":false,"duration":2}],"layers":[],"initialState":{"affineTransform":[1,0,0,1,0,0],"masksToBounds":false,"rotation":0,"scale":1,"position":{"pointX":451.5,"pointY":323.5},"width":481,"sublayerTransform":[1,0,0,0,0,1,0,0,0,0,1,0,0,0,0,1],"contentsRect":{"y":0,"x":0,"width":1,"height":1},"opacity":1,"edgeAntialiasingMask":0,"height":49,"hidden":false,"anchorPoint":{"pointX":0.9303534303534303,"pointY":-5.479591836734694}},"texture":"D9D14FC9304218BE071BFC518A61B9F3"}]},{"animations":[{"timeOffset":0,"beginTime":0,"repeatCount":0,"animations":[{"timeOffset":0,"from":{"scalar":0.008},"beginTime":0,"repeatCount":0,"fillMode":"both","duration":2,"autoreverses":false,"timingFunction":"EaseInEaseOut","property":"zPosition","to":{"scalar":0.008}}],"fillMode":"both","autoreverses":false,"duration":2}],"initialState":{"affineTransform":[1,0,0,1,0,0],"masksToBounds":false,"rotation":0,"scale":1,"position":{"pointX":511.5,"pointY":383.5},"width":903,"sublayerTransform":[1,0,0,0,0,1,0,0,0,0,1,0,0,0,0,1],"contentsRect":{"y":0,"x":0,"width":1,"height":1},"opacity":1,"edgeAntialiasingMask":251658240,"height":647,"hidden":false,"anchorPoint":{"pointX":0.5,"pointY":0.5}},"layers":[{"animations":[{"timeOffset":0,"beginTime":0,"repeatCount":0,"animations":[{"timeOffset":0,"from":{"scalar":1},"beginTime":0,"repeatCount":0,"fillMode":"forwards","duration":2,"autoreverses":false,"timingFunction":"EaseInEaseOut","property":"opacity","to":{"scalar":0}},{"timeOffset":0,"from":{"scalar":true},"beginTime":1.998,"repeatCount":0,"fillMode":"forwards","property":"hidden","autoreverses":false,"duration":0.002000000000000002,"to":{"scalar":true}}],"fillMode":"both","autoreverses":false,"duration":2}],"layers":[],"initialState":{"affineTransform":[1,0,0,1,0,0],"masksToBounds":false,"rotation":0,"scale":1,"position":{"pointX":451.5,"pointY":323.5},"width":851,"sublayerTransform":[1,0,0,0,0,1,0,0,0,0,1,0,0,0,0,1],"contentsRect":{"y":0,"x":0,"width":1,"height":1},"opacity":1,"edgeAntialiasingMask":0,"height":49,"hidden":false,"anchorPoint":{"pointX":0.5258519388954171,"pointY":-1.948979591836735}},"texture":"1271778CB81AA6A50AC86F5223E5A8DE"}]},{"animations":[{"timeOffset":0,"beginTime":0,"repeatCount":0,"animations":[{"timeOffset":0,"from":{"scalar":0.009000000000000001},"beginTime":0,"repeatCount":0,"fillMode":"both","duration":2,"autoreverses":false,"timingFunction":"EaseInEaseOut","property":"zPosition","to":{"scalar":0.009000000000000001}}],"fillMode":"both","autoreverses":false,"duration":2}],"initialState":{"affineTransform":[1,0,0,1,0,0],"masksToBounds":false,"rotation":0,"scale":1,"position":{"pointX":512,"pointY":116},"width":968,"sublayerTransform":[1,0,0,0,0,1,0,0,0,0,1,0,0,0,0,1],"contentsRect":{"y":0,"x":0,"width":1,"height":1},"opacity":1,"edgeAntialiasingMask":251658240,"height":192,"hidden":false,"anchorPoint":{"pointX":0.5,"pointY":0.5}},"layers":[{"animations":[{"timeOffset":0,"beginTime":0,"repeatCount":0,"animations":[{"timeOffset":0,"from":{"scalar":0},"beginTime":0,"repeatCount":0,"fillMode":"both","duration":2,"autoreverses":false,"timingFunction":"EaseInEaseOut","property":"opacity","to":{"scalar":1}},{"timeOffset":0,"from":{"scalar":false},"beginTime":0,"repeatCount":0,"fillMode":"forwards","property":"hidden","autoreverses":false,"duration":2,"to":{"scalar":false}}],"fillMode":"both","autoreverses":false,"duration":2}],"layers":[],"initialState":{"affineTransform":[1,0,0,1,0,0],"masksToBounds":false,"rotation":0,"scale":1,"position":{"pointX":484,"pointY":96},"width":605,"sublayerTransform":[1,0,0,0,0,1,0,0,0,0,1,0,0,0,0,1],"contentsRect":{"y":0,"x":0,"width":1,"height":1},"opacity":1,"edgeAntialiasingMask":0,"height":55,"hidden":true,"anchorPoint":{"pointX":0.4991735537190083,"pointY":0.4727272727272727}},"texture":"017C668F998B7F15E9E4969BA01E1547"}]},{"animations":[{"timeOffset":0,"beginTime":0,"repeatCount":0,"animations":[{"timeOffset":0,"from":{"scalar":0.01},"beginTime":0,"repeatCount":0,"fillMode":"both","duration":2,"autoreverses":false,"timingFunction":"EaseInEaseOut","property":"zPosition","to":{"scalar":0.01}}],"fillMode":"both","autoreverses":false,"duration":2}],"initialState":{"affineTransform":[1,0,0,1,0,0],"masksToBounds":false,"rotation":0,"scale":1,"position":{"pointX":512,"pointY":463},"width":968,"sublayerTransform":[1,0,0,0,0,1,0,0,0,0,1,0,0,0,0,1],"contentsRect":{"y":0,"x":0,"width":1,"height":1},"opacity":1,"edgeAntialiasingMask":251658240,"height":496,"hidden":false,"anchorPoint":{"pointX":0.5,"pointY":0.5}},"layers":[{"animations":[{"timeOffset":0,"beginTime":0,"repeatCount":0,"animations":[{"timeOffset":0,"from":{"scalar":0},"beginTime":0,"repeatCount":0,"fillMode":"both","duration":2,"autoreverses":false,"timingFunction":"EaseInEaseOut","property":"opacity","to":{"scalar":1}},{"timeOffset":0,"from":{"scalar":false},"beginTime":0,"repeatCount":0,"fillMode":"forwards","property":"hidden","autoreverses":false,"duration":2,"to":{"scalar":false}}],"fillMode":"both","autoreverses":false,"duration":2}],"layers":[],"initialState":{"affineTransform":[1,0,0,1,0,0],"masksToBounds":false,"rotation":0,"scale":1,"position":{"pointX":483.9999999999999,"pointY":248},"width":915,"sublayerTransform":[1,0,0,0,0,1,0,0,0,0,1,0,0,0,0,1],"contentsRect":{"y":0,"x":0,"width":1,"height":1},"opacity":1,"edgeAntialiasingMask":0,"height":47,"hidden":true,"anchorPoint":{"pointX":0.526775956284153,"pointY":5}},"texture":"DC8E691884F75FE1807FEC32BDA4A5F3"}]},{"animations":[{"timeOffset":0,"beginTime":0,"repeatCount":0,"animations":[{"timeOffset":0,"from":{"scalar":0.011},"beginTime":0,"repeatCount":0,"fillMode":"both","duration":2,"autoreverses":false,"timingFunction":"EaseInEaseOut","property":"zPosition","to":{"scalar":0.011}}],"fillMode":"both","autoreverses":false,"duration":2}],"initialState":{"affineTransform":[1,0,0,1,0,0],"masksToBounds":false,"rotation":0,"scale":1,"position":{"pointX":512,"pointY":463},"width":968,"sublayerTransform":[1,0,0,0,0,1,0,0,0,0,1,0,0,0,0,1],"contentsRect":{"y":0,"x":0,"width":1,"height":1},"opacity":1,"edgeAntialiasingMask":251658240,"height":496,"hidden":false,"anchorPoint":{"pointX":0.5,"pointY":0.5}},"layers":[{"animations":[{"timeOffset":0,"beginTime":0,"repeatCount":0,"animations":[{"timeOffset":0,"from":{"scalar":0},"beginTime":0,"repeatCount":0,"fillMode":"both","duration":2,"autoreverses":false,"timingFunction":"EaseInEaseOut","property":"opacity","to":{"scalar":1}},{"timeOffset":0,"from":{"scalar":false},"beginTime":0,"repeatCount":0,"fillMode":"forwards","property":"hidden","autoreverses":false,"duration":2,"to":{"scalar":false}}],"fillMode":"both","autoreverses":false,"duration":2}],"layers":[],"initialState":{"affineTransform":[1,0,0,1,0,0],"masksToBounds":false,"rotation":0,"scale":1,"position":{"pointX":484,"pointY":248},"width":686,"sublayerTransform":[1,0,0,0,0,1,0,0,0,0,1,0,0,0,0,1],"contentsRect":{"y":0,"x":0,"width":1,"height":1},"opacity":1,"edgeAntialiasingMask":0,"height":45,"hidden":true,"anchorPoint":{"pointX":0.6457725947521866,"pointY":-0.2888888888888889}},"texture":"57815644117D774ADB2AE5FF763EFF69"}]},{"animations":[{"timeOffset":0,"beginTime":0,"repeatCount":0,"animations":[{"timeOffset":0,"from":{"scalar":0.012},"beginTime":0,"repeatCount":0,"fillMode":"both","duration":2,"autoreverses":false,"timingFunction":"EaseInEaseOut","property":"zPosition","to":{"scalar":0.012}}],"fillMode":"both","autoreverses":false,"duration":2}],"initialState":{"affineTransform":[1,0,0,1,0,0],"masksToBounds":false,"rotation":0,"scale":1,"position":{"pointX":512,"pointY":463},"width":968,"sublayerTransform":[1,0,0,0,0,1,0,0,0,0,1,0,0,0,0,1],"contentsRect":{"y":0,"x":0,"width":1,"height":1},"opacity":1,"edgeAntialiasingMask":251658240,"height":496,"hidden":false,"anchorPoint":{"pointX":0.5,"pointY":0.5}},"layers":[{"animations":[{"timeOffset":0,"beginTime":0,"repeatCount":0,"animations":[{"timeOffset":0,"from":{"scalar":0},"beginTime":0,"repeatCount":0,"fillMode":"both","duration":2,"autoreverses":false,"timingFunction":"EaseInEaseOut","property":"opacity","to":{"scalar":1}},{"timeOffset":0,"from":{"scalar":false},"beginTime":0,"repeatCount":0,"fillMode":"forwards","property":"hidden","autoreverses":false,"duration":2,"to":{"scalar":false}}],"fillMode":"both","autoreverses":false,"duration":2}],"layers":[],"initialState":{"affineTransform":[1,0,0,1,0,0],"masksToBounds":false,"rotation":0,"scale":1,"position":{"pointX":484,"pointY":248},"width":793,"sublayerTransform":[1,0,0,0,0,1,0,0,0,0,1,0,0,0,0,1],"contentsRect":{"y":0,"x":0,"width":1,"height":1},"opacity":1,"edgeAntialiasingMask":0,"height":51,"hidden":true,"anchorPoint":{"pointX":0.605296343001261,"pointY":1.196078431372549}},"texture":"3516134BABE37B77441AD23AA08AB556"}]},{"animations":[{"timeOffset":0,"beginTime":0,"repeatCount":0,"animations":[{"timeOffset":0,"from":{"scalar":0.013},"beginTime":0,"repeatCount":0,"fillMode":"both","duration":2,"autoreverses":false,"timingFunction":"EaseInEaseOut","property":"zPosition","to":{"scalar":0.013}}],"fillMode":"both","autoreverses":false,"duration":2}],"initialState":{"affineTransform":[1,0,0,1,0,0],"masksToBounds":false,"rotation":0,"scale":1,"position":{"pointX":512,"pointY":463},"width":968,"sublayerTransform":[1,0,0,0,0,1,0,0,0,0,1,0,0,0,0,1],"contentsRect":{"y":0,"x":0,"width":1,"height":1},"opacity":1,"edgeAntialiasingMask":251658240,"height":496,"hidden":false,"anchorPoint":{"pointX":0.5,"pointY":0.5}},"layers":[{"animations":[{"timeOffset":0,"beginTime":0,"repeatCount":0,"animations":[{"timeOffset":0,"from":{"scalar":0},"beginTime":0,"repeatCount":0,"fillMode":"both","duration":2,"autoreverses":false,"timingFunction":"EaseInEaseOut","property":"opacity","to":{"scalar":1}},{"timeOffset":0,"from":{"scalar":false},"beginTime":0,"repeatCount":0,"fillMode":"forwards","property":"hidden","autoreverses":false,"duration":2,"to":{"scalar":false}}],"fillMode":"both","autoreverses":false,"duration":2}],"layers":[],"initialState":{"affineTransform":[1,0,0,1,0,0],"masksToBounds":false,"rotation":0,"scale":1,"position":{"pointX":484,"pointY":248},"width":513,"sublayerTransform":[1,0,0,0,0,1,0,0,0,0,1,0,0,0,0,1],"contentsRect":{"y":0,"x":0,"width":1,"height":1},"opacity":1,"edgeAntialiasingMask":0,"height":36,"hidden":true,"anchorPoint":{"pointX":0.935672514619883,"pointY":4.611111111111111}},"texture":"3566B8F5A3052C3CFC02C486841F1578"}]},{"animations":[{"timeOffset":0,"beginTime":0,"repeatCount":0,"animations":[{"timeOffset":0,"from":{"scalar":0.014},"beginTime":0,"repeatCount":0,"fillMode":"both","duration":2,"autoreverses":false,"timingFunction":"EaseInEaseOut","property":"zPosition","to":{"scalar":0.014}}],"fillMode":"both","autoreverses":false,"duration":2}],"initialState":{"affineTransform":[1,0,0,1,0,0],"masksToBounds":false,"rotation":0,"scale":1,"position":{"pointX":512,"pointY":463},"width":968,"sublayerTransform":[1,0,0,0,0,1,0,0,0,0,1,0,0,0,0,1],"contentsRect":{"y":0,"x":0,"width":1,"height":1},"opacity":1,"edgeAntialiasingMask":251658240,"height":496,"hidden":false,"anchorPoint":{"pointX":0.5,"pointY":0.5}},"layers":[{"animations":[{"timeOffset":0,"beginTime":0,"repeatCount":0,"animations":[{"timeOffset":0,"from":{"scalar":0},"beginTime":0,"repeatCount":0,"fillMode":"both","duration":2,"autoreverses":false,"timingFunction":"EaseInEaseOut","property":"opacity","to":{"scalar":1}},{"timeOffset":0,"from":{"scalar":false},"beginTime":0,"repeatCount":0,"fillMode":"forwards","property":"hidden","autoreverses":false,"duration":2,"to":{"scalar":false}}],"fillMode":"both","autoreverses":false,"duration":2}],"layers":[],"initialState":{"affineTransform":[1,0,0,1,0,0],"masksToBounds":false,"rotation":0,"scale":1,"position":{"pointX":484,"pointY":248},"width":511,"sublayerTransform":[1,0,0,0,0,1,0,0,0,0,1,0,0,0,0,1],"contentsRect":{"y":0,"x":0,"width":1,"height":1},"opacity":1,"edgeAntialiasingMask":0,"height":45,"hidden":true,"anchorPoint":{"pointX":0.8669275929549902,"pointY":-4.266666666666667}},"texture":"109D68C7090F2FDAA0DF4E7A1E94D247"}]},{"animations":[{"timeOffset":0,"beginTime":0,"repeatCount":0,"animations":[{"timeOffset":0,"from":{"scalar":0.015},"beginTime":0,"repeatCount":0,"fillMode":"both","duration":2,"autoreverses":false,"timingFunction":"EaseInEaseOut","property":"zPosition","to":{"scalar":0.015}}],"fillMode":"both","autoreverses":false,"duration":2}],"initialState":{"affineTransform":[1,0,0,1,0,0],"masksToBounds":false,"rotation":0,"scale":1,"position":{"pointX":512,"pointY":463},"width":968,"sublayerTransform":[1,0,0,0,0,1,0,0,0,0,1,0,0,0,0,1],"contentsRect":{"y":0,"x":0,"width":1,"height":1},"opacity":1,"edgeAntialiasingMask":251658240,"height":496,"hidden":false,"anchorPoint":{"pointX":0.5,"pointY":0.5}},"layers":[{"animations":[{"timeOffset":0,"beginTime":0,"repeatCount":0,"animations":[{"timeOffset":0,"from":{"scalar":0},"beginTime":0,"repeatCount":0,"fillMode":"both","duration":2,"autoreverses":false,"timingFunction":"EaseInEaseOut","property":"opacity","to":{"scalar":1}},{"timeOffset":0,"from":{"scalar":false},"beginTime":0,"repeatCount":0,"fillMode":"forwards","property":"hidden","autoreverses":false,"duration":2,"to":{"scalar":false}}],"fillMode":"both","autoreverses":false,"duration":2}],"layers":[],"initialState":{"affineTransform":[1,0,0,1,0,0],"masksToBounds":false,"rotation":0,"scale":1,"position":{"pointX":484,"pointY":248},"width":954,"sublayerTransform":[1,0,0,0,0,1,0,0,0,0,1,0,0,0,0,1],"contentsRect":{"y":0,"x":0,"width":1,"height":1},"opacity":1,"edgeAntialiasingMask":0,"height":51,"hidden":true,"anchorPoint":{"pointX":0.5031446540880503,"pointY":-2.313725490196079}},"texture":"40771467E7D8A9D109D564F1F5A5F8AD"}]}]},"effects":[],"duration":2,"type":"transition","name":"apple:magic-move-implied-motion-path","objectID":"0"}],"automaticPlay":false,"hyperlinks":[],"accessibility":[{"text":"Key objective: To provide users with a simple and easy to use site where they can purchase fan apparel of varying styles, fits, and sizes.","targetRectangle":{"y":64,"x":100.080000641035,"width":821.4396093749999,"height":198.0000078678131}},{"text":"Role: User Researcher, Visual Designer, UX Designer, UI Designer","targetRectangle":{"y":262.0000078678131,"x":100.080000641035,"width":792.9968749999999,"height":172.4800050258636}},{"text":"Tools: pen & paper, Adobe Illustrator, Sketch, Keynote, FaceTime, MarkDown, InVision","targetRectangle":{"y":434.4800128936768,"x":100.080000641035,"width":827.7448437500001,"height":172.4800050258636}},{"text":"Project Timeline: 1 week","targetRectangle":{"y":606.9600179195404,"x":100.080000641035,"width":443.8568749999999,"height":106.4800024032593}}],"baseLayer":{"animations":[],"initialState":{"affineTransform":[1,0,0,1,0,0],"masksToBounds":false,"rotation":0,"scale":1,"position":{"pointX":512,"pointY":384},"width":1024,"sublayerTransform":[1,0,0,0,0,1,0,0,0,0,1,0,0,0,0,1],"contentsRect":{"y":0,"x":0,"width":1,"height":1},"opacity":1,"edgeAntialiasingMask":251658240,"height":768,"hidden":false,"anchorPoint":{"pointX":0.5,"pointY":0.5}},"objectID":"0","layers":[{"animations":[],"initialState":{"affineTransform":[1,0,0,1,0,0],"masksToBounds":false,"rotation":0,"scale":1,"position":{"pointX":512,"pointY":384},"width":1024,"sublayerTransform":[1,0,0,0,0,1,0,0,0,0,1,-0.0004922987690640373,0,0,0,1],"contentsRect":{"y":0,"x":0,"width":1,"height":1},"opacity":1,"edgeAntialiasingMask":251658240,"height":768,"hidden":false,"anchorPoint":{"pointX":0.5,"pointY":0.5}},"layers":[{"animations":[],"initialState":{"affineTransform":[1,0,0,1,0,0],"masksToBounds":false,"rotation":0,"scale":1,"position":{"pointX":512,"pointY":384},"width":1024,"sublayerTransform":[1,0,0,0,0,1,0,0,0,0,1,0,0,0,0,1],"contentsRect":{"y":0,"x":0,"width":1,"height":1},"opacity":1,"edgeAntialiasingMask":251658240,"height":768,"hidden":false,"anchorPoint":{"pointX":0.5,"pointY":0.5}},"layers":[{"animations":[],"layers":[],"initialState":{"affineTransform":[1,0,0,1,0,0],"masksToBounds":false,"rotation":0,"scale":1,"position":{"pointX":512,"pointY":384},"width":1024,"sublayerTransform":[1,0,0,0,0,1,0,0,0,0,1,0,0,0,0,1],"contentsRect":{"y":0,"x":0,"width":1,"height":1},"opacity":1,"edgeAntialiasingMask":0,"height":768,"hidden":false,"anchorPoint":{"pointX":0.5,"pointY":0.5}},"texture":"498E23C82CA78A4BCD7BA88E5243B6FC"}]}]},{"animations":[],"initialState":{"affineTransform":[1,0,0,1,0,0],"masksToBounds":false,"rotation":0,"scale":1,"position":{"pointX":511.5,"pointY":383.5},"width":903,"sublayerTransform":[1,0,0,0,0,1,0,0,0,0,1,0,0,0,0,1],"contentsRect":{"y":0,"x":0,"width":1,"height":1},"opacity":1,"edgeAntialiasingMask":251658240,"height":647,"hidden":false,"anchorPoint":{"pointX":0.5,"pointY":0.5}},"layers":[{"animations":[],"layers":[],"initialState":{"affineTransform":[1,0,0,1,0,0],"masksToBounds":false,"rotation":0,"scale":1,"position":{"pointX":451.5000000000001,"pointY":323.5},"width":846,"sublayerTransform":[1,0,0,0,0,1,0,0,0,0,1,0,0,0,0,1],"contentsRect":{"y":0,"x":0,"width":1,"height":1},"opacity":1,"edgeAntialiasingMask":0,"height":50,"hidden":false,"anchorPoint":{"pointX":0.5289598108747046,"pointY":6.31}},"texture":"5C6FE352E1A9717F70C38CF9737A0768"}]},{"animations":[],"initialState":{"affineTransform":[1,0,0,1,0,0],"masksToBounds":false,"rotation":0,"scale":1,"position":{"pointX":511.5,"pointY":383.5},"width":903,"sublayerTransform":[1,0,0,0,0,1,0,0,0,0,1,0,0,0,0,1],"contentsRect":{"y":0,"x":0,"width":1,"height":1},"opacity":1,"edgeAntialiasingMask":251658240,"height":647,"hidden":false,"anchorPoint":{"pointX":0.5,"pointY":0.5}},"layers":[{"animations":[],"layers":[],"initialState":{"affineTransform":[1,0,0,1,0,0],"masksToBounds":false,"rotation":0,"scale":1,"position":{"pointX":451.5,"pointY":323.5},"width":806,"sublayerTransform":[1,0,0,0,0,1,0,0,0,0,1,0,0,0,0,1],"contentsRect":{"y":0,"x":0,"width":1,"height":1},"opacity":1,"edgeAntialiasingMask":0,"height":44,"hidden":false,"anchorPoint":{"pointX":0.510545905707196,"pointY":5.534090909090909}},"texture":"45AED0194D76030045A33608F1C5935F"}]},{"animations":[],"initialState":{"affineTransform":[1,0,0,1,0,0],"masksToBounds":false,"rotation":0,"scale":1,"position":{"pointX":511.5,"pointY":383.5},"width":903,"sublayerTransform":[1,0,0,0,0,1,0,0,0,0,1,0,0,0,0,1],"contentsRect":{"y":0,"x":0,"width":1,"height":1},"opacity":1,"edgeAntialiasingMask":251658240,"height":647,"hidden":false,"anchorPoint":{"pointX":0.5,"pointY":0.5}},"layers":[{"animations":[],"layers":[],"initialState":{"affineTransform":[1,0,0,1,0,0],"masksToBounds":false,"rotation":0,"scale":1,"position":{"pointX":451.5,"pointY":323.5},"width":777,"sublayerTransform":[1,0,0,0,0,1,0,0,0,0,1,0,0,0,0,1],"contentsRect":{"y":0,"x":0,"width":1,"height":1},"opacity":1,"edgeAntialiasingMask":0,"height":44,"hidden":false,"anchorPoint":{"pointX":0.5296010296010296,"pointY":4.034090909090909}},"texture":"594DD3763D6DF4DD8985F7652A5E1E22"}]},{"animations":[],"initialState":{"affineTransform":[1,0,0,1,0,0],"masksToBounds":false,"rotation":0,"scale":1,"position":{"pointX":511.5,"pointY":383.5},"width":903,"sublayerTransform":[1,0,0,0,0,1,0,0,0,0,1,0,0,0,0,1],"contentsRect":{"y":0,"x":0,"width":1,"height":1},"opacity":1,"edgeAntialiasingMask":251658240,"height":647,"hidden":false,"anchorPoint":{"pointX":0.5,"pointY":0.5}},"layers":[{"animations":[],"layers":[],"initialState":{"affineTransform":[1,0,0,1,0,0],"masksToBounds":false,"rotation":0,"scale":1,"position":{"pointX":451.5,"pointY":323.5},"width":400,"sublayerTransform":[1,0,0,0,0,1,0,0,0,0,1,0,0,0,0,1],"contentsRect":{"y":0,"x":0,"width":1,"height":1},"opacity":1,"edgeAntialiasingMask":0,"height":43,"hidden":false,"anchorPoint":{"pointX":1.02875,"pointY":0.1046511627906977}},"texture":"B47C72EEE3C5FCFD1CE0804F1B8DC033"}]},{"animations":[],"initialState":{"affineTransform":[1,0,0,1,0,0],"masksToBounds":false,"rotation":0,"scale":1,"position":{"pointX":511.5,"pointY":383.5},"width":903,"sublayerTransform":[1,0,0,0,0,1,0,0,0,0,1,0,0,0,0,1],"contentsRect":{"y":0,"x":0,"width":1,"height":1},"opacity":1,"edgeAntialiasingMask":251658240,"height":647,"hidden":false,"anchorPoint":{"pointX":0.5,"pointY":0.5}},"layers":[{"animations":[],"layers":[],"initialState":{"affineTransform":[1,0,0,1,0,0],"masksToBounds":false,"rotation":0,"scale":1,"position":{"pointX":451.5000000000001,"pointY":323.5},"width":819,"sublayerTransform":[1,0,0,0,0,1,0,0,0,0,1,0,0,0,0,1],"contentsRect":{"y":0,"x":0,"width":1,"height":1},"opacity":1,"edgeAntialiasingMask":0,"height":49,"hidden":false,"anchorPoint":{"pointX":0.5463980463980465,"pointY":1.561224489795918}},"texture":"D984BE9F520E639DDDAE398166E6BAAD"}]},{"animations":[],"initialState":{"affineTransform":[1,0,0,1,0,0],"masksToBounds":false,"rotation":0,"scale":1,"position":{"pointX":511.5,"pointY":383.5},"width":903,"sublayerTransform":[1,0,0,0,0,1,0,0,0,0,1,0,0,0,0,1],"contentsRect":{"y":0,"x":0,"width":1,"height":1},"opacity":1,"edgeAntialiasingMask":251658240,"height":647,"hidden":false,"anchorPoint":{"pointX":0.5,"pointY":0.5}},"layers":[{"animations":[],"layers":[],"initialState":{"affineTransform":[1,0,0,1,0,0],"masksToBounds":false,"rotation":0,"scale":1,"position":{"pointX":451.5,"pointY":323.5},"width":741,"sublayerTransform":[1,0,0,0,0,1,0,0,0,0,1,0,0,0,0,1],"contentsRect":{"y":0,"x":0,"width":1,"height":1},"opacity":1,"edgeAntialiasingMask":0,"height":44,"hidden":false,"anchorPoint":{"pointX":0.5553306342780027,"pointY":-3.806818181818182}},"texture":"A3E4EFD9794FB7642995D2C77814E950"}]},{"animations":[],"initialState":{"affineTransform":[1,0,0,1,0,0],"masksToBounds":false,"rotation":0,"scale":1,"position":{"pointX":511.5,"pointY":383.5},"width":903,"sublayerTransform":[1,0,0,0,0,1,0,0,0,0,1,0,0,0,0,1],"contentsRect":{"y":0,"x":0,"width":1,"height":1},"opacity":1,"edgeAntialiasingMask":251658240,"height":647,"hidden":false,"anchorPoint":{"pointX":0.5,"pointY":0.5}},"layers":[{"animations":[],"layers":[],"initialState":{"affineTransform":[1,0,0,1,0,0],"masksToBounds":false,"rotation":0,"scale":1,"position":{"pointX":451.5,"pointY":323.5},"width":481,"sublayerTransform":[1,0,0,0,0,1,0,0,0,0,1,0,0,0,0,1],"contentsRect":{"y":0,"x":0,"width":1,"height":1},"opacity":1,"edgeAntialiasingMask":0,"height":49,"hidden":false,"anchorPoint":{"pointX":0.9303534303534303,"pointY":-5.479591836734694}},"texture":"D9D14FC9304218BE071BFC518A61B9F3"}]},{"animations":[],"initialState":{"affineTransform":[1,0,0,1,0,0],"masksToBounds":false,"rotation":0,"scale":1,"position":{"pointX":511.5,"pointY":383.5},"width":903,"sublayerTransform":[1,0,0,0,0,1,0,0,0,0,1,0,0,0,0,1],"contentsRect":{"y":0,"x":0,"width":1,"height":1},"opacity":1,"edgeAntialiasingMask":251658240,"height":647,"hidden":false,"anchorPoint":{"pointX":0.5,"pointY":0.5}},"layers":[{"animations":[],"layers":[],"initialState":{"affineTransform":[1,0,0,1,0,0],"masksToBounds":false,"rotation":0,"scale":1,"position":{"pointX":451.5,"pointY":323.5},"width":851,"sublayerTransform":[1,0,0,0,0,1,0,0,0,0,1,0,0,0,0,1],"contentsRect":{"y":0,"x":0,"width":1,"height":1},"opacity":1,"edgeAntialiasingMask":0,"height":49,"hidden":false,"anchorPoint":{"pointX":0.5258519388954171,"pointY":-1.948979591836735}},"texture":"1271778CB81AA6A50AC86F5223E5A8DE"}]},{"animations":[],"initialState":{"affineTransform":[1,0,0,1,0,0],"masksToBounds":false,"rotation":0,"scale":1,"position":{"pointX":512,"pointY":116},"width":968,"sublayerTransform":[1,0,0,0,0,1,0,0,0,0,1,0,0,0,0,1],"contentsRect":{"y":0,"x":0,"width":1,"height":1},"opacity":1,"edgeAntialiasingMask":251658240,"height":192,"hidden":false,"anchorPoint":{"pointX":0.5,"pointY":0.5}},"layers":[{"animations":[],"layers":[],"initialState":{"affineTransform":[1,0,0,1,0,0],"masksToBounds":false,"rotation":0,"scale":1,"position":{"pointX":484,"pointY":96},"width":605,"sublayerTransform":[1,0,0,0,0,1,0,0,0,0,1,0,0,0,0,1],"contentsRect":{"y":0,"x":0,"width":1,"height":1},"opacity":1,"edgeAntialiasingMask":0,"height":55,"hidden":true,"anchorPoint":{"pointX":0.4991735537190083,"pointY":0.4727272727272727}},"texture":"017C668F998B7F15E9E4969BA01E1547"}]},{"animations":[],"initialState":{"affineTransform":[1,0,0,1,0,0],"masksToBounds":false,"rotation":0,"scale":1,"position":{"pointX":512,"pointY":463},"width":968,"sublayerTransform":[1,0,0,0,0,1,0,0,0,0,1,0,0,0,0,1],"contentsRect":{"y":0,"x":0,"width":1,"height":1},"opacity":1,"edgeAntialiasingMask":251658240,"height":496,"hidden":false,"anchorPoint":{"pointX":0.5,"pointY":0.5}},"layers":[{"animations":[],"layers":[],"initialState":{"affineTransform":[1,0,0,1,0,0],"masksToBounds":false,"rotation":0,"scale":1,"position":{"pointX":483.9999999999999,"pointY":248},"width":915,"sublayerTransform":[1,0,0,0,0,1,0,0,0,0,1,0,0,0,0,1],"contentsRect":{"y":0,"x":0,"width":1,"height":1},"opacity":1,"edgeAntialiasingMask":0,"height":47,"hidden":true,"anchorPoint":{"pointX":0.526775956284153,"pointY":5}},"texture":"DC8E691884F75FE1807FEC32BDA4A5F3"}]},{"animations":[],"initialState":{"affineTransform":[1,0,0,1,0,0],"masksToBounds":false,"rotation":0,"scale":1,"position":{"pointX":512,"pointY":463},"width":968,"sublayerTransform":[1,0,0,0,0,1,0,0,0,0,1,0,0,0,0,1],"contentsRect":{"y":0,"x":0,"width":1,"height":1},"opacity":1,"edgeAntialiasingMask":251658240,"height":496,"hidden":false,"anchorPoint":{"pointX":0.5,"pointY":0.5}},"layers":[{"animations":[],"layers":[],"initialState":{"affineTransform":[1,0,0,1,0,0],"masksToBounds":false,"rotation":0,"scale":1,"position":{"pointX":484,"pointY":248},"width":686,"sublayerTransform":[1,0,0,0,0,1,0,0,0,0,1,0,0,0,0,1],"contentsRect":{"y":0,"x":0,"width":1,"height":1},"opacity":1,"edgeAntialiasingMask":0,"height":45,"hidden":true,"anchorPoint":{"pointX":0.6457725947521866,"pointY":-0.2888888888888889}},"texture":"57815644117D774ADB2AE5FF763EFF69"}]},{"animations":[],"initialState":{"affineTransform":[1,0,0,1,0,0],"masksToBounds":false,"rotation":0,"scale":1,"position":{"pointX":512,"pointY":463},"width":968,"sublayerTransform":[1,0,0,0,0,1,0,0,0,0,1,0,0,0,0,1],"contentsRect":{"y":0,"x":0,"width":1,"height":1},"opacity":1,"edgeAntialiasingMask":251658240,"height":496,"hidden":false,"anchorPoint":{"pointX":0.5,"pointY":0.5}},"layers":[{"animations":[],"layers":[],"initialState":{"affineTransform":[1,0,0,1,0,0],"masksToBounds":false,"rotation":0,"scale":1,"position":{"pointX":484,"pointY":248},"width":793,"sublayerTransform":[1,0,0,0,0,1,0,0,0,0,1,0,0,0,0,1],"contentsRect":{"y":0,"x":0,"width":1,"height":1},"opacity":1,"edgeAntialiasingMask":0,"height":51,"hidden":true,"anchorPoint":{"pointX":0.605296343001261,"pointY":1.196078431372549}},"texture":"3516134BABE37B77441AD23AA08AB556"}]},{"animations":[],"initialState":{"affineTransform":[1,0,0,1,0,0],"masksToBounds":false,"rotation":0,"scale":1,"position":{"pointX":512,"pointY":463},"width":968,"sublayerTransform":[1,0,0,0,0,1,0,0,0,0,1,0,0,0,0,1],"contentsRect":{"y":0,"x":0,"width":1,"height":1},"opacity":1,"edgeAntialiasingMask":251658240,"height":496,"hidden":false,"anchorPoint":{"pointX":0.5,"pointY":0.5}},"layers":[{"animations":[],"layers":[],"initialState":{"affineTransform":[1,0,0,1,0,0],"masksToBounds":false,"rotation":0,"scale":1,"position":{"pointX":484,"pointY":248},"width":513,"sublayerTransform":[1,0,0,0,0,1,0,0,0,0,1,0,0,0,0,1],"contentsRect":{"y":0,"x":0,"width":1,"height":1},"opacity":1,"edgeAntialiasingMask":0,"height":36,"hidden":true,"anchorPoint":{"pointX":0.935672514619883,"pointY":4.611111111111111}},"texture":"3566B8F5A3052C3CFC02C486841F1578"}]},{"animations":[],"initialState":{"affineTransform":[1,0,0,1,0,0],"masksToBounds":false,"rotation":0,"scale":1,"position":{"pointX":512,"pointY":463},"width":968,"sublayerTransform":[1,0,0,0,0,1,0,0,0,0,1,0,0,0,0,1],"contentsRect":{"y":0,"x":0,"width":1,"height":1},"opacity":1,"edgeAntialiasingMask":251658240,"height":496,"hidden":false,"anchorPoint":{"pointX":0.5,"pointY":0.5}},"layers":[{"animations":[],"layers":[],"initialState":{"affineTransform":[1,0,0,1,0,0],"masksToBounds":false,"rotation":0,"scale":1,"position":{"pointX":484,"pointY":248},"width":511,"sublayerTransform":[1,0,0,0,0,1,0,0,0,0,1,0,0,0,0,1],"contentsRect":{"y":0,"x":0,"width":1,"height":1},"opacity":1,"edgeAntialiasingMask":0,"height":45,"hidden":true,"anchorPoint":{"pointX":0.8669275929549902,"pointY":-4.266666666666667}},"texture":"109D68C7090F2FDAA0DF4E7A1E94D247"}]},{"animations":[],"initialState":{"affineTransform":[1,0,0,1,0,0],"masksToBounds":false,"rotation":0,"scale":1,"position":{"pointX":512,"pointY":463},"width":968,"sublayerTransform":[1,0,0,0,0,1,0,0,0,0,1,0,0,0,0,1],"contentsRect":{"y":0,"x":0,"width":1,"height":1},"opacity":1,"edgeAntialiasingMask":251658240,"height":496,"hidden":false,"anchorPoint":{"pointX":0.5,"pointY":0.5}},"layers":[{"animations":[],"layers":[],"initialState":{"affineTransform":[1,0,0,1,0,0],"masksToBounds":false,"rotation":0,"scale":1,"position":{"pointX":484,"pointY":248},"width":954,"sublayerTransform":[1,0,0,0,0,1,0,0,0,0,1,0,0,0,0,1],"contentsRect":{"y":0,"x":0,"width":1,"height":1},"opacity":1,"edgeAntialiasingMask":0,"height":51,"hidden":true,"anchorPoint":{"pointX":0.5031446540880503,"pointY":-2.313725490196079}},"texture":"40771467E7D8A9D109D564F1F5A5F8AD"}]}]}}]}